<?xml version="1.0"?>
<ruleset name="WordPress Coding Standards">
	<description>Generally-applicable sniffs for WordPress plugins.</description>

	<!-- What to scan -->
	<!-- What to scan -->
	<file>./theme/</file>

	<!-- Folders -->
	<exclude-pattern>*/css/*</exclude-pattern>
	<exclude-pattern>*/fonts/*</exclude-pattern>
	<exclude-pattern>*/img/*</exclude-pattern>
	<exclude-pattern>*/js/*</exclude-pattern>
	<exclude-pattern>*/languages/*</exclude-pattern>
	<exclude-pattern>*/audit-quiz/*</exclude-pattern>

	<!-- Files -->
	<exclude-pattern>*.json</exclude-pattern>
	<exclude-pattern>*.lock</exclude-pattern>
	<exclude-pattern>*.md</exclude-pattern>
	<exclude-pattern>*.less</exclude-pattern>
	<exclude-pattern>*.css</exclude-pattern>
	<exclude-pattern>*.png</exclude-pattern>

	<config name="php_memory_limit" value="1024M"/>

	<!-- How to scan -->
	<!-- Usage instructions: https://github.com/squizlabs/PHP_CodeSniffer/wiki/Usage -->
	<!-- Annotated ruleset: https://github.com/squizlabs/PHP_CodeSniffer/wiki/Annotated-ruleset.xml -->
	<arg value="sp"/> <!-- Show sniff and progress -->
	<!-- <arg name="basepath" value="./"/> -->
	<!-- Strip the file paths down to the relevant bit -->
	<arg name="colors"/>
	<arg name="extensions" value="php"/>
	<arg name="parallel" value="16"/><!-- Enables parallel processing when available for faster results. -->

	<!-- Rules: Check PHP version compatibility -->
	<!-- https://github.com/PHPCompatibility/PHPCompatibility#sniffing-your-code-for-compatibility-with-specific-php-versions -->
	<config name="testVersion" value="7.4-"/>

	<!-- Rules: Check PHP version compatibility-->
	<!-- https://github.com/PHPCompatibility/PHPCompatibilityWP -->
	<!-- <rule ref="PHPCompatibilityWP"/> -->
	<rule ref="WordPress"/>

	<!-- Rules: WordPress Coding Standards -->
	<!-- https://github.com/WordPress-Coding-Standards/WordPress-Coding-Standards -->
	<!-- https://github.com/WordPress-Coding-Standards/WordPress-Coding-Standards/wiki/Customizable-sniff-properties -->
	<config name="minimum_supported_wp_version" value="5.4"/>
	<rule ref="WordPress-Extra"/>
	<rule ref="WordPress">
		<!-- <exclude name="Generic.WhiteSpace.DisallowSpaceIndent"/> -->
	</rule>
	<rule ref="WordPress.WP.I18n">
		<properties>
			<!-- Value: replace the text domain used. -->
			<property name="text_domain" type="array" value="mappers"/>
		</properties>
	</rule>
	<rule ref="WordPress.WhiteSpace.ControlStructureSpacing">
		<properties>
			<property name="blank_line_check" value="true"/>
		</properties>
	</rule>
	
	<rule ref="Squiz.Commenting.InlineComment.InvalidEndChar">
		<severity>0</severity>
	</rule>
</ruleset>
